phaseaug/__init__.py
phaseaug/phaseaug.py
phaseaug-1.0.1.dist-info/LICENSE
phaseaug-1.0.1.dist-info/METADATA
phaseaug-1.0.1.dist-info/WHEEL
phaseaug-1.0.1.dist-info/top_level.txt
phaseaug-1.0.1.dist-info/RECORD
