Metadata-Version: 2.1
Name: phaseaug
Version: 1.0.1
Summary: PhaseAug: A Differentiable Augmentation for Speech Synthesis to Simulate One-to-Many Mapping
Home-page: https://github.com/mindslab-ai/phaseaug
Author: junjun3518
Author-email: junjun3518@gmail.com
License: UNKNOWN
Keywords: torch,pytorch,augmentation,diffaugment,speech synthesis,vocoder
Platform: UNKNOWN
Requires-Python: >=3
License-File: LICENSE
Requires-Dist: torch
Requires-Dist: alias-free-torch
